setup.py
PthMsn_Client_v1.egg-info/PKG-INFO
PthMsn_Client_v1.egg-info/SOURCES.txt
PthMsn_Client_v1.egg-info/dependency_links.txt
PthMsn_Client_v1.egg-info/requires.txt
PthMsn_Client_v1.egg-info/top_level.txt
src/__init__.py
src/client_start.py
src/client/__init__.py
src/client/add_friend.py
src/client/client_storage.py
src/client/del_friend.py
src/client/exchange_proto.py
src/client/main_client_gui.py
src/client/main_client_gui_conv.py
src/client/uname_dialog.py
src/common/__init__.py
src/common/decorators.py
src/common/errors.py
src/common/metaclasses.py
src/common/utils.py
src/common/variables.py
src/log/__init__.py
src/log/client_log_config.py